audiblez/__init__.py
audiblez/cli.py
audiblez/core.py
audiblez/ui.py
audiblez/voices.py
audiblez-0.4.9.dist-info/LICENSE
audiblez-0.4.9.dist-info/METADATA
audiblez-0.4.9.dist-info/WHEEL
audiblez-0.4.9.dist-info/entry_points.txt
audiblez-0.4.9.dist-info/RECORD
