Metadata-Version: 2.3
Name: audiblez
Version: 0.4.9
Summary: Generate audiobooks from e-books (epub to wav/m4b)
Home-page: https://claudio.uk/posts/epub-to-audiobook.html
Author: Claudio Santini
Author-email: hireclaudio@gmail.com
Requires-Python: >=3.9,<3.13
Classifier: Programming Language :: Python :: 3
Classifier: Programming Language :: Python :: 3.9
Classifier: Programming Language :: Python :: 3.10
Classifier: Programming Language :: Python :: 3.11
Classifier: Programming Language :: Python :: 3.12
Requires-Dist: bs4 (>=0.0.2,<0.0.3)
Requires-Dist: ebooklib (>=0.18,<0.19)
Requires-Dist: kokoro (>=0.7.9,<0.8.0)
Requires-Dist: misaki[zh] (>=0.7.10,<0.8.0)
Requires-Dist: pick (>=2.4.0,<3.0.0)
Requires-Dist: soundfile (>=0.13.1,<0.14.0)
Requires-Dist: spacy (>=3.8.3,<4.0.0)
Requires-Dist: tabulate (>=0.9.0,<0.10.0)
Project-URL: Documentation, https://github.com/santinic/audiblez
Project-URL: Issues, https://github.com/santinic/audiblez/issues
Project-URL: Repository, https://github.com/santinic/audiblez
